havenondemand/__init__.py
havenondemand/errorcodes.py
havenondemand/hodclient.py
havenondemand/hodresponseparser.py
havenondemand-2.0.1.post0.dist-info/DESCRIPTION.rst
havenondemand-2.0.1.post0.dist-info/METADATA
havenondemand-2.0.1.post0.dist-info/RECORD
havenondemand-2.0.1.post0.dist-info/WHEEL
havenondemand-2.0.1.post0.dist-info/entry_points.txt
havenondemand-2.0.1.post0.dist-info/metadata.json
havenondemand-2.0.1.post0.dist-info/top_level.txt
havenondemand-2.0.1.post0.dist-info/zip-safe
