Metadata-Version: 2.0
Name: havenondemand
Version: 2.0.1.post0
Summary: Haven OnDemand Python client library
Home-page: http://havenondemand.com
Author: Phong Vu, Tyler Nappy
Author-email: van-phong.vu@hpe.com, tyler.nappy@hpe.com
License: UNKNOWN
Keywords: Haven OnDemand havenondemand hod
Platform: UNKNOWN
Requires-Dist: requests
